ai_helper_rena/__init__.py
ai_helper_rena/client.py
ai_helper_rena/exceptions.py
ai_helper_rena/history.py
ai_helper_rena/utils.py
ai_helper_rena-0.1.0.dist-info/METADATA
ai_helper_rena-0.1.0.dist-info/WHEEL
ai_helper_rena-0.1.0.dist-info/top_level.txt
ai_helper_rena-0.1.0.dist-info/RECORD
